odoo/addons/sale_order_archive/README.rst
odoo/addons/sale_order_archive/__init__.py
odoo/addons/sale_order_archive/__manifest__.py
odoo/addons/sale_order_archive/i18n/ca.po
odoo/addons/sale_order_archive/i18n/de.po
odoo/addons/sale_order_archive/i18n/es.po
odoo/addons/sale_order_archive/i18n/sale_order_archive.pot
odoo/addons/sale_order_archive/models/__init__.py
odoo/addons/sale_order_archive/models/sale_order.py
odoo/addons/sale_order_archive/readme/CONTRIBUTORS.rst
odoo/addons/sale_order_archive/readme/DESCRIPTION.rst
odoo/addons/sale_order_archive/readme/USAGE.rst
odoo/addons/sale_order_archive/static/description/icon.png
odoo/addons/sale_order_archive/static/description/index.html
odoo/addons/sale_order_archive/views/sale_order.xml
odoo11_addon_sale_order_archive-11.0.1.0.0.99.dev10.dist-info/METADATA
odoo11_addon_sale_order_archive-11.0.1.0.0.99.dev10.dist-info/WHEEL
odoo11_addon_sale_order_archive-11.0.1.0.0.99.dev10.dist-info/top_level.txt
odoo11_addon_sale_order_archive-11.0.1.0.0.99.dev10.dist-info/RECORD
